foresee/TO-DO-LIST
foresee/__init__.py
foresee/dev_test.py
foresee/qcheck.ipynb
foresee/qcheck.py
foresee/temp.py
foresee/test.py
foresee/test_app.py
foresee/data/__init__.py
foresee/data/basic_time_series_data.csv
foresee/data/test_data.csv
foresee/data/test_data_light.csv
foresee/examples/__init__.py
foresee/examples/basic tutorial [ multi column input dataframe ].ipynb
foresee/examples/basic tutorial [ one time series as a single column dataframe ].ipynb
"foresee/examples/basic tutorial, multi column input dataframe.ipynb"
"foresee/examples/basic tutorial, one column input dataframe.ipynb"
foresee/examples/drop file to forecast.ipynb
foresee/models/__init__.py
foresee/models/ewm.py
foresee/models/fft.py
foresee/models/holt_winters.py
foresee/models/models_util.py
foresee/models/param_optimizer.py
foresee/models/prophet.py
foresee/models/sarimax.py
foresee/models/.vscode/settings.json
foresee/params/__init__.py
foresee/params/constants.py
foresee/params/model_params.json
foresee/params/param_config.json
foresee/scripts/__init__.py
foresee/scripts/compose.py
foresee/scripts/fitter.py
foresee/scripts/main.py
foresee/scripts/utils.py
foresee/webapp/__init__.py
foresee/webapp/app.py
foresee/webapp/dash_app.py
foresee-0.1.0a9.dist-info/LICENSE
foresee-0.1.0a9.dist-info/METADATA
foresee-0.1.0a9.dist-info/WHEEL
foresee-0.1.0a9.dist-info/top_level.txt
foresee-0.1.0a9.dist-info/RECORD
