Metadata-Version: 2.1
Name: foresee
Version: 0.1.0a9
Summary: Generate forecasts using several time series forecasting models in python.
Home-page: https://github.com/HamidM6/foresee
Author: Hamid Mohammadi
Author-email: hmohammadi6545@gmail.com
License: UNKNOWN
Platform: UNKNOWN
Classifier: Development Status :: 3 - Alpha
Classifier: Programming Language :: Python :: 3
Classifier: License :: OSI Approved :: MIT License
Classifier: Operating System :: OS Independent
